kurs_dolara/__init__.py
kurs_dolara/main.py
kurs_dolara-1.2.1.dist-info/METADATA
kurs_dolara-1.2.1.dist-info/WHEEL
kurs_dolara-1.2.1.dist-info/entry_points.txt
kurs_dolara-1.2.1.dist-info/RECORD
