Metadata-Version: 2.4
Name: kurs-dolara
Version: 1.2.1
Summary: Program koji prikazuje trenutni kurs dolara prema podacima sa web sajta Centralne banke BiH
Project-URL: github, https://github.com/bringout/kurs_dolara
Author-email: Ernad Husremovic <hernad@bring.out.ba>
Requires-Python: >=3.12
Requires-Dist: requests>=2.32.5
Requires-Dist: textual>=5.3.0
